pysimlin-0.5.0.dist-info/WHEEL
pysimlin-0.5.0.dist-info/top_level.txt
pysimlin-0.5.0.dist-info/METADATA
pysimlin-0.5.0.dist-info/RECORD
pysimlin-0.5.0.dist-info/licenses/LICENSE
simlin/json_types.py
simlin/project.py
simlin/analysis.py
simlin/types.py
simlin/_dt.py
simlin/py.typed
simlin/sim.py
simlin/model.py
simlin/_ffi.py
simlin/_ffi_build.py
simlin/__init__.py
simlin/run.py
simlin/errors.py
simlin/json_converter.py
simlin/_clib.abi3.so
