Metadata-Version: 2.4
Name: pysimlin
Version: 0.5.0
Summary: Python bindings for the Simlin system dynamics simulation engine
Author: The Simlin Authors
Maintainer: The Simlin Authors
License: Apache-2.0
Project-URL: Homepage, https://github.com/bpowers/simlin
Project-URL: Documentation, https://github.com/bpowers/simlin/tree/main/src/pysimlin
Project-URL: Repository, https://github.com/bpowers/simlin
Project-URL: Issues, https://github.com/bpowers/simlin/issues
Classifier: Development Status :: 4 - Beta
Classifier: Intended Audience :: Science/Research
Classifier: Intended Audience :: Developers
Classifier: License :: OSI Approved :: Apache Software License
Classifier: Operating System :: MacOS :: MacOS X
Classifier: Operating System :: POSIX :: Linux
Classifier: Programming Language :: Python :: 3
Classifier: Programming Language :: Python :: 3.11
Classifier: Programming Language :: Python :: 3.12
Classifier: Programming Language :: Python :: 3.13
Classifier: Topic :: Scientific/Engineering
Classifier: Topic :: Scientific/Engineering :: Mathematics
Classifier: Topic :: Software Development :: Libraries :: Python Modules
Classifier: Typing :: Typed
Requires-Python: >=3.11
License-File: LICENSE
Requires-Dist: cffi>=1.15.0
Requires-Dist: pandas>=1.5.0
Requires-Dist: numpy>=1.22.0
Requires-Dist: cattrs>=24.1.0
Provides-Extra: test
Requires-Dist: pytest>=7.0.0; extra == "test"
Requires-Dist: pytest-cov>=4.0.0; extra == "test"
Requires-Dist: hypothesis>=6.100.0; extra == "test"
Requires-Dist: jsonschema>=4.20.0; extra == "test"
Provides-Extra: dev
Requires-Dist: pysimlin[test]; extra == "dev"
Requires-Dist: mypy>=1.5.0; extra == "dev"
Requires-Dist: black>=23.0.0; extra == "dev"
Requires-Dist: ruff>=0.1.0; extra == "dev"
Requires-Dist: pandas-stubs>=2.0.0; extra == "dev"
Requires-Dist: types-setuptools; extra == "dev"
Requires-Dist: build>=1.0.0; extra == "dev"
Dynamic: license-file
